[
  {
    "id": 1,
    "icon": "wave",
    "title": "Struggling with a breakup",
    "text": ""
  },
  {
    "id": 2,
    "icon": "wave",
    "title": "Lacking time and energy to do the things you want to do",
    "text": ""
  },
  {
    "id": 3,
    "icon": "wave",
    "title": "Recovering from a breakdown",
    "text": ""
  },
  {
    "id": 4,
    "icon": "wave",
    "title": "Living with depression",
    "text": ""
  },
  {
    "id": 5,
    "icon": "wave",
    "title": "I'm living with a disability and need support.",
    "text": ""
  }
]